{
  "platform": "taobao",
  "screens": [
    {
      "screen": 1,
      "texts": [
        "10:32",
        "1",
        "0",
        ":",
        "32",
        "星期三",
        "2月25日",
        "雾",
        "-12°"
      ],
      "raw": [
        {
          "text": "10:32",
          "bounds": "[72,336][699,656]",
          "src": "cd"
        },
        {
          "text": "1",
          "bounds": "[72,336][176,656]",
          "src": "text"
        },
        {
          "text": "0",
          "bounds": "[176,336][333,656]",
          "src": "text"
        },
        {
          "text": ":",
          "bounds": "[333,336][405,656]",
          "src": "text"
        },
        {
          "text": "32",
          "bounds": "[405,336][699,656]",
          "src": "text"
        },
        {
          "text": "星期三",
          "bounds": "[78,267][363,396]",
          "src": "text"
        },
        {
          "text": "2月25日",
          "bounds": "[84,626][308,707]",
          "src": "text"
        },
        {
          "text": "雾",
          "bounds": "[338,626][422,710]",
          "src": "cd"
        },
        {
          "text": "-12°",
          "bounds": "[428,626][531,707]",
          "src": "text"
        }
      ]
    }
  ],
  "total_screens": 1
}